CHANGELOG.md
aiovmmanager/__init__.py
aiovmmanager/base.py
aiovmmanager/vm6.py
aiovmmanager-0.1.1.dist-info/LICENSE
aiovmmanager-0.1.1.dist-info/METADATA
aiovmmanager-0.1.1.dist-info/WHEEL
aiovmmanager-0.1.1.dist-info/RECORD
