Metadata-Version: 2.1
Name: aiovmmanager
Version: 0.1.1
Summary: Async lib based on aiohttp for working with the VMmanager6 API
Home-page: https://github.com/MOIS3Y/aiovmmanager
License: MIT
Keywords: vmmanager,ispsystem,kvm,virtualisation
Author: MOIS3Y
Author-email: stepan@zhukovsky.me
Requires-Python: >=3.9,<4.0
Classifier: License :: OSI Approved :: MIT License
Classifier: Programming Language :: Python :: 3
Classifier: Programming Language :: Python :: 3.9
Classifier: Programming Language :: Python :: 3.10
Classifier: Programming Language :: Python :: 3.11
Classifier: Programming Language :: Python :: 3.12
Requires-Dist: aiohttp (>=3.8.1,<4.0.0)
Project-URL: Repository, https://github.com/MOIS3Y/aiovmmanager
